{"generated_at_utc":"2026-07-01T07:23:43+00:00","today":"2026-07-01","latest_date":"2026-07-01","dates":{"2026-06-29":{"date":"2026-06-29","alert_count":2,"feature_count":42,"max_color":3,"max_code":3,"nowcasting_count":0,"has_nowcasting":false,"has_geojson":true,"has_archive":true,"file":"2026-06-29.geojson","codes":[2,3],"phenomena":["temperaturi extreme"],"archive_alert_count":3},"2026-06-30":{"date":"2026-06-30","alert_count":1,"feature_count":42,"max_color":3,"max_code":3,"nowcasting_count":0,"has_nowcasting":false,"has_geojson":true,"has_archive":true,"file":"2026-06-30.geojson","codes":[2,3],"phenomena":["temperaturi extreme"],"archive_alert_count":8},"2026-07-01":{"date":"2026-07-01","alert_count":2,"feature_count":65,"max_color":2,"max_code":2,"nowcasting_count":0,"has_nowcasting":false,"has_geojson":true,"has_archive":true,"file":"2026-07-01.geojson","codes":[1,2],"phenomena":["ploi/vijelii","temperaturi extreme"],"archive_alert_count":11},"2026-07-02":{"date":"2026-07-02","alert_count":3,"feature_count":94,"max_color":2,"max_code":2,"nowcasting_count":0,"has_nowcasting":false,"has_geojson":true,"has_archive":true,"file":"2026-07-02.geojson","codes":[1,2],"phenomena":["ploi/vijelii","temperaturi extreme"],"archive_alert_count":5},"2026-07-03":{"date":"2026-07-03","alert_count":1,"feature_count":42,"max_color":1,"max_code":1,"nowcasting_count":0,"has_nowcasting":false,"has_geojson":true,"has_archive":true,"file":"2026-07-03.geojson","codes":[1],"phenomena":["ploi/vijelii"],"archive_alert_count":2}}}